cheopslcs/__init__.py
cheopslcs/lcsim.py
cheopslcs-0.9.dist-info/LICENSE
cheopslcs-0.9.dist-info/METADATA
cheopslcs-0.9.dist-info/WHEEL
cheopslcs-0.9.dist-info/top_level.txt
cheopslcs-0.9.dist-info/RECORD
