Metadata-Version: 2.2
Name: cheopslcs
Version: 0.9
Summary: A simple CHEOPS light curve simulator that creates transit and phase-curve light curves.
Author-email: Judith Korth <judithkorth@gmail.com>, Hannu Parviainen <hpparvi@gmail.com>
License: GPLv3
Classifier: Topic :: Scientific/Engineering
Classifier: Intended Audience :: Science/Research
Classifier: Intended Audience :: Developers
Classifier: Development Status :: 5 - Production/Stable
Classifier: License :: OSI Approved :: GNU General Public License v3 (GPLv3)
Classifier: Operating System :: OS Independent
Classifier: Programming Language :: Python
Requires-Python: >=3.10
License-File: LICENSE
Requires-Dist: meepmeep>=0.7.2
Requires-Dist: pytransit>=2.6.13
Requires-Dist: numpy
